task_core/__init__.py
task_core/base.py
task_core/cmd.py
task_core/exceptions.py
task_core/inventory.py
task_core/logging.py
task_core/manager.py
task_core/schema.py
task_core/service.py
task_core/tasks.py
task_core/utils.py
task_core/tests/__init__.py
task_core/tests/test_base.py
task_core/tests/test_inventory.py
task_core/tests/test_manager.py
task_core/tests/test_schema.py
task_core/tests/test_service.py
task_core/tests/test_tasks.py
task_core/tests/test_utils.py
task_core-0.2.1.data/data/share/task-core/contrib/rpm-build.sh
task_core-0.2.1.data/data/share/task-core/contrib/task-core.spec
task_core-0.2.1.data/data/share/task-core/contrib/container-build/Containerfile
task_core-0.2.1.data/data/share/task-core/contrib/container-build/builder.sh
task_core-0.2.1.data/data/share/task-core/contrib/example-tools/deployed2ansible.py
task_core-0.2.1.data/data/share/task-core/contrib/example-tools/deployed2directord.py
task_core-0.2.1.data/data/share/task-core/contrib/example-tools/directord2ansible.py
task_core-0.2.1.data/data/share/task-core/examples/ansible/test-playbook.yml
task_core-0.2.1.data/data/share/task-core/examples/directord/README.md
task_core-0.2.1.data/data/share/task-core/examples/directord/basic/2node_directord_catalog.yaml
task_core-0.2.1.data/data/share/task-core/examples/directord/basic/2node_inventory.yaml
task_core-0.2.1.data/data/share/task-core/examples/directord/basic/2node_options.yaml
task_core-0.2.1.data/data/share/task-core/examples/directord/basic/2node_roles.yaml
task_core-0.2.1.data/data/share/task-core/examples/directord/basic/ansible_inventory.yaml
task_core-0.2.1.data/data/share/task-core/examples/directord/basic/basic_inventory.yaml
task_core-0.2.1.data/data/share/task-core/examples/directord/basic/basic_options.yaml
task_core-0.2.1.data/data/share/task-core/examples/directord/basic/basic_roles.yaml
task_core-0.2.1.data/data/share/task-core/examples/directord/basic/directord_catalog.yaml
task_core-0.2.1.dist-info/AUTHORS
task_core-0.2.1.dist-info/LICENSE
task_core-0.2.1.dist-info/METADATA
task_core-0.2.1.dist-info/WHEEL
task_core-0.2.1.dist-info/entry_points.txt
task_core-0.2.1.dist-info/pbr.json
task_core-0.2.1.dist-info/top_level.txt
task_core-0.2.1.dist-info/RECORD
