Metadata-Version: 2.1
Name: task-core
Version: 0.2.1
Summary: task core
Home-page: https://github.com/Directord/task-core
Author: Alex Schultz
Author-email: aschultz@next-development.com
License: UNKNOWN
Platform: UNKNOWN
Classifier: Development Status :: 1 - Planning
Classifier: Intended Audience :: Developers
Classifier: Intended Audience :: Information Technology
Classifier: Intended Audience :: System Administrators
Classifier: License :: OSI Approved :: Apache Software License
Classifier: Operating System :: POSIX :: Linux
Classifier: Programming Language :: Python
Classifier: Programming Language :: Python :: 3
Classifier: Programming Language :: Python :: 3.6
Classifier: Programming Language :: Python :: 3.7
Classifier: Programming Language :: Python :: 3.8
Classifier: Programming Language :: Python :: 3 :: Only
Classifier: Topic :: Utilities
Requires-Python: >=3.6
Requires-Dist: pbr (!=2.1.0,>=2.0.0)
Requires-Dist: networkx
Requires-Dist: taskflow
Requires-Dist: pyyaml
Requires-Dist: stevedore
Requires-Dist: jsonschema (>=3.2.0)
